leaf_common/__init__.py
leaf_common/asyncio/__init__.py
leaf_common/asyncio/async_to_sync_generator.py
leaf_common/asyncio/asyncio_executor.py
leaf_common/asyncio/asyncio_executor_pool.py
leaf_common/candidates/__init__.py
leaf_common/candidates/constants.py
leaf_common/candidates/representation_types.py
leaf_common/config/__init__.py
leaf_common/config/config_filter.py
leaf_common/config/config_filter_chain.py
leaf_common/config/config_handler.py
leaf_common/config/dictionary_overlay.py
leaf_common/config/environment_defaults.py
leaf_common/config/file_of_class.py
leaf_common/config/resolver.py
leaf_common/config/resolver_util.py
leaf_common/evaluation/__init__.py
leaf_common/evaluation/component_evaluator.py
leaf_common/evaluation/metrics_merger.py
leaf_common/filters/__init__.py
leaf_common/filters/composite_string_filter.py
leaf_common/filters/inclusionary_replacement_string_filter.py
leaf_common/filters/replacement_string_filter.py
leaf_common/filters/sanitizer_util.py
leaf_common/filters/string_filter.py
leaf_common/filters/strip_whitespace_string_filter.py
leaf_common/filters/tensorflow_field_name_filter.py
leaf_common/fitness/__init__.py
leaf_common/fitness/candidate_metrics_provider.py
leaf_common/fitness/cmp_to_key.py
leaf_common/fitness/comparator.py
leaf_common/fitness/fitness_objective.py
leaf_common/fitness/fitness_objectives.py
leaf_common/fitness/fitness_objectives_builder.py
leaf_common/fitness/fitness_objectives_from_config.py
leaf_common/fitness/metrics_based_individual_comparator.py
leaf_common/fitness/metrics_provider.py
leaf_common/fitness/none_comparator.py
leaf_common/fitness/number_comparator.py
leaf_common/fitness/reversed_comparator.py
leaf_common/log_utils/__init__.py
leaf_common/log_utils/message_type.py
leaf_common/log_utils/structured_message.py
leaf_common/logging/__init__.py
leaf_common/logging/example_logging_config.hocon
leaf_common/logging/logging_setup.py
leaf_common/logging/stream_to_logger.py
leaf_common/parsers/__init__.py
leaf_common-1.2.32.dist-info/licenses/LICENSE.txt
leaf_common-1.2.32.dist-info/METADATA
leaf_common-1.2.32.dist-info/WHEEL
leaf_common-1.2.32.dist-info/top_level.txt
leaf_common-1.2.32.dist-info/RECORD
