Metadata-Version: 2.4
Name: leaf-common
Version: 1.2.32
Summary: LEAF team common code library
Author-email: Dan Fink <Daniel.Fink@cognizant.com>
License-Expression: Apache-2.0
Project-URL: Homepage, https://github.com/cognizant-ai-lab/leaf-common
Project-URL: Repository, https://github.com/cognizant-ai-lab/leaf-common
Project-URL: Documentation, https://github.com/cognizant-ai-lab/leaf-common#readme
Keywords: utility,interfaces
Classifier: Programming Language :: Python :: 3
Classifier: Operating System :: OS Independent
Classifier: Development Status :: 5 - Production/Stable
Classifier: Intended Audience :: Developers
Requires-Python: >=3.10
License-File: LICENSE.txt
Requires-Dist: grpcio>=1.48.2
Requires-Dist: pyOpenSSL>=23.1.1
Requires-Dist: PyJWT>=2.9.0
Requires-Dist: cryptography>=42.0.8
Requires-Dist: hvac>=1.1.0
Requires-Dist: pytz>=2022.7.1
Requires-Dist: ruamel.yaml>=0.17.21
Requires-Dist: pyhocon>=0.3.60
Requires-Dist: Deprecated>=1.2.13
Dynamic: license-file
